main.py
ablpywrapper-0.0.2.dist-info/METADATA
ablpywrapper-0.0.2.dist-info/WHEEL
ablpywrapper-0.0.2.dist-info/top_level.txt
ablpywrapper-0.0.2.dist-info/RECORD
