Metadata-Version: 2.1
Name: ablpywrapper
Version: 0.0.2
Summary: Astro botlist python api wrapper
Home-page: https://github.com/botlists/ablpywrapper
Author: Sell
License: UNKNOWN
Platform: UNKNOWN
Classifier: Programming Language :: Python :: 3
Classifier: Programming Language :: Python :: 3.6
Classifier: Programming Language :: Python :: 3.7
Classifier: Operating System :: OS Independent
Requires-Dist: requests
Provides-Extra: dev
Requires-Dist: pytest (>=3.7) ; extra == 'dev'
